pollination/annual_sky_radiation/__init__.py
pollination/annual_sky_radiation/_raytracing.py
pollination/annual_sky_radiation/entry.py
pollination_annual_sky_radiation-0.1.7.dist-info/LICENSE
pollination_annual_sky_radiation-0.1.7.dist-info/METADATA
pollination_annual_sky_radiation-0.1.7.dist-info/WHEEL
pollination_annual_sky_radiation-0.1.7.dist-info/top_level.txt
pollination_annual_sky_radiation-0.1.7.dist-info/RECORD
