Metadata-Version: 2.1
Name: pollination-annual-sky-radiation
Version: 0.1.7
Summary: Annual Sky Radiation recipe for Pollination.
Home-page: https://github.com/pollination/annual-sky-radiation
Author: ladybug-tools
Author-email: info@ladybug.tools
Maintainer: mostapha, ladybug-tools
Maintainer-email: mostapha@ladybug.tools, info@ladybug.tools
License: PolyForm Shield License 1.0.0, https://polyformproject.org/wp-content/uploads/2020/06/PolyForm-Shield-1.0.0.txt
Project-URL: icon, https://raw.githubusercontent.com/ladybug-tools/artwork/master/icons_components/honeybee/png/annualrecipe.png
Project-URL: docker, https://hub.docker.com/r/ladybugtools/honeybee-radiance
Keywords: honeybee,radiance,ladybug-tools,daylight,annual-sky-radiation
Platform: UNKNOWN
Requires-Dist: pollination-honeybee-radiance (>=0.16.6)
Requires-Dist: pollination-alias (>=0.10.0)
